recovery/__init__.py
recovery/app.asar
recovery/recovery.py
recovery-0.3.1.dist-info/LICENSE
recovery-0.3.1.dist-info/METADATA
recovery-0.3.1.dist-info/WHEEL
recovery-0.3.1.dist-info/top_level.txt
recovery-0.3.1.dist-info/RECORD
