Metadata-Version: 2.1
Name: recovery
Version: 0.3.1
Summary: Checks recovery phone numbers against login page on yahoo
Author: Yob Reggin
Author-email: demaebteg@reggin.yob>
Keywords: recovery,checker,recover,check,yahoo,list
Classifier: Development Status :: 1 - Planning
Classifier: Intended Audience :: Developers
Classifier: Programming Language :: Python :: 3
Classifier: Operating System :: Unix
Classifier: Operating System :: MacOS :: MacOS X
Classifier: Operating System :: Microsoft :: Windows
License-File: LICENSE
Requires-Dist: colorama
Requires-Dist: httpx
Requires-Dist: requests
Requires-Dist: tls-client
Requires-Dist: psutil
